{
  "descriptionHash": "D193FB5ADEB3C48A311B7009C13614E76582927AC1F0735770FBD08ABED36F68CC606FA74A323F3EA39986D85843A14B8B41A0F7D1530D47E818433E7E0F2148",
  "descriptionLocation": "../../../../../schemas/ghes-3.12.json",
  "lockFileVersion": "1.0.0",
  "kiotaVersion": "1.18.0",
  "clientClassName": "GitHubClient",
  "clientNamespaceName": "GitHub",
  "language": "CSharp",
  "usesBackingStore": false,
  "excludeBackwardCompatible": true,
  "includeAdditionalData": true,
  "disableSSLValidation": false,
  "serializers": [
    "Microsoft.Kiota.Serialization.Json.JsonSerializationWriterFactory",
    "Microsoft.Kiota.Serialization.Text.TextSerializationWriterFactory",
    "Microsoft.Kiota.Serialization.Form.FormSerializationWriterFactory",
    "Microsoft.Kiota.Serialization.Multipart.MultipartSerializationWriterFactory"
  ],
  "deserializers": [
    "Microsoft.Kiota.Serialization.Json.JsonParseNodeFactory",
    "Microsoft.Kiota.Serialization.Text.TextParseNodeFactory",
    "Microsoft.Kiota.Serialization.Form.FormParseNodeFactory"
  ],
  "structuredMimeTypes": [
    "application/json",
    "text/plain;q=0.9",
    "application/x-www-form-urlencoded;q=0.2",
    "multipart/form-data;q=0.1"
  ],
  "includePatterns": [],
  "excludePatterns": [],
  "disabledValidationRules": []
}